stoys/__init__.py
stoys/config.py
stoys/deps/__init__.py
stoys/deps/_embedded/stoys-scala_2.12-0.5.0-SNAPSHOT-spark-shaded.jar
stoys/deps/_embedded/stoys-spark-du_2.12-0.5.0-SNAPSHOT-spark-shaded.jar
stoys/deps/_embedded/stoys-spark_2.12-0.5.0-SNAPSHOT-spark-shaded.jar
stoys/deps/_embedded/stoys-ui.js
stoys/deps/common.py
stoys/deps/download.py
stoys/deps/use.py
stoys/init.py
stoys/integration/ipython.py
stoys/integration/notebook.py
stoys/integration/pandas.py
stoys/integration/pyspark.py
stoys/pmf.py
stoys/py.typed
stoys/scala/__init__.py
stoys/scala/arbitrary.py
stoys/scala/jackson.py
stoys/scala/reflection.py
stoys/scala/strings.py
stoys/spark/__init__.py
stoys/spark/aggsum/__init__.py
stoys/spark/aggsum/aggsum.py
stoys/spark/aggsum/aggsum_config.py
stoys/spark/aggsum/aggsum_result.py
stoys/spark/datasets.py
stoys/spark/dp/__init__.py
stoys/spark/dp/dp.py
stoys/spark/dp/dp_config.py
stoys/spark/dp/dp_result.py
stoys/spark/dp/dp_type_inference_config.py
stoys/spark/dq/__init__.py
stoys/spark/dq/dq.py
stoys/spark/dq/dq_config.py
stoys/spark/dq/dq_field.py
stoys/spark/dq/dq_join.py
stoys/spark/dq/dq_join_result.py
stoys/spark/dq/dq_join_type.py
stoys/spark/dq/dq_result.py
stoys/spark/dq/dq_rule.py
stoys/spark/dq/dq_rules.py
stoys/spark/reshape.py
stoys/spark/reshape_config.py
stoys/spark/spark_io.py
stoys/spark/spark_io_config.py
stoys/spark/table_name.py
stoys/ui/aggsum_ui.py
stoys/ui/dp_ui.py
stoys/ui/dq_join_result_ui.py
stoys/ui/dq_result_ui.py
stoys/ui/pmf_ui.py
stoys/ui/utils.py
stoys/utils/case_class.py
stoys/utils/data_types.py
stoys/utils/json.py
stoys/utils/jvm.py
stoys/utils/py4j.py
stoys/utils/python.py
stoys/utils/scala_compat.py
stoys/utils/spark.py
stoys/utils/spark_session.py
stoys-0.4.6.dist-info/entry_points.txt
stoys-0.4.6.dist-info/LICENSE
stoys-0.4.6.dist-info/WHEEL
stoys-0.4.6.dist-info/METADATA
stoys-0.4.6.dist-info/RECORD
